setup.py
statsite/__init__.py
statsite/aggregator.py
statsite/aliveness.py
statsite/collector.py
statsite/metrics.py
statsite/metrics_store.py
statsite/parser.py
statsite/statsite.py
statsite/util.py
statsite.egg-info/PKG-INFO
statsite.egg-info/SOURCES.txt
statsite.egg-info/dependency_links.txt
statsite.egg-info/entry_points.txt
statsite.egg-info/top_level.txt
statsite/bin/__init__.py
statsite/bin/statsite.py