Metadata-Version: 1.0
Name: statsite
Version: 0.4.0
Summary: Statistics server which sends data to Graphite.
Home-page: https://github.com/kiip/statsite
Author: Kiip
Author-email: biz@kiip.me
License: UNKNOWN
Keywords: statsite,graphite,graph,metrics
Platform: UNKNOWN
Classifier: Development Status :: 4 - Beta
Classifier: Intended Audience :: System Administrators
Classifier: Intended Audience :: Developers
Classifier: License :: OSI Approved :: MIT License
Classifier: Operating System :: OS Independent
Classifier: Programming Language :: Python
Classifier: Topic :: System :: Monitoring
Classifier: Topic :: System :: Systems Administration
